{
  "clips": [
    {
      "caption": "在北京时间1月2日的NBA常规赛中，爵士队主场以127比90，大比分胜出独行侠，成功收获一场37分大胜",
      "imagePath": "output/1704567069557053000/online-image-0.jpg",
      "audioPath": "output/1704567069557053000/audio-0.wav",
      "imageInfo": {
        "provider": "cdn.vox-cdn.com",
        "name": "3 things as the Mavericks soldier on against the Jazz in game two ...",
        "encodingFormat": "jpeg"
      },
      "audioInfo": {
        "audio_duration": 10
      }
    },
    {
      "caption": "原本精神饱满的独行侠队在面对爵士的挑衅中阴沟翻船，其1.8亿的两大球员共投21球仅得18分的表现，让人感到惋惜",
      "imagePath": "output/1704567069557053000/online-image-1.jpg",
      "audioPath": "output/1704567069557053000/audio-1.wav",
      "imageInfo": {
        "provider": "file.qiumiwu.com",
        "name": "NBA季后赛独行侠vs爵士G4全场录像回放集锦(2022年4月24日） - 球迷屋",
        "encodingFormat": "jpeg"
      },
      "audioInfo": {
        "audio_duration": 11
      }
    },
    {
      "caption": "在本场比赛中，爵士队斗志昂扬，常规赛小克确立了9分领先优势，次节东契奇也开启个人模式，单节轰下10分",
      "imagePath": "output/1704567069557053000/online-image-2.jpg",
      "audioPath": "output/1704567069557053000/audio-2.wav",
      "imageInfo": {
        "provider": "img1.gtimg.com",
        "name": "犹他爵士队-NBA中国官方网站",
        "encodingFormat": "jpeg"
      },
      "audioInfo": {
        "audio_duration": 10
      }
    },
    {
      "caption": "然而，独行侠队在易边再战中，尽管在东契奇的带动下曾一度将劣势缩小到3分，但是爵士队依然坚持攻势，以马尔卡宁的连续三分和其他球员的出色表现，将比分拉大到领先20分以上，最终以37分的优势轻取独行侠",
      "imagePath": "output/1704567069557053000/online-image-3.jpg",
      "audioPath": "output/1704567069557053000/audio-3.wav",
      "imageInfo": {
        "provider": "k.sinaimg.cn",
        "name": "[NBA季后赛]独行侠Vs爵士_新浪图片",
        "encodingFormat": "jpeg"
      },
      "audioInfo": {
        "audio_duration": 19
      }
    },
    {
      "caption": "这场比赛之后，众多球迷对独行侠的两笔超赚交易表示质疑，认为他们在这两笔运作中全亏了",
      "imagePath": "output/1704567069557053000/online-image-4.jpg",
      "audioPath": "output/1704567069557053000/audio-4.wav",
      "imageInfo": {
        "provider": "file.qiumiwu.com",
        "name": "NBA记者：布伦森可与独行侠签下5年2000万合同 其他球队无法签下此合同 - 球迷屋",
        "encodingFormat": "jpeg"
      },
      "audioInfo": {
        "audio_duration": 8
      }
    }
  ]
}